jsonfield/VERSION
jsonfield/__init__.py
jsonfield/fields.py
jsonfield/forms.py
jsonfield/models.py
jsonfield/utils.py
jsonfield/widgets.py
jsonfield/templatetags/__init__.py
jsonfield/templatetags/jsonify.py
jsonfield/tests/__init__.py
jsonfield/tests/test_fields.py
jsonfield/tests/test_forms.py
jsonfield/tests/jsonfield_test_app/__init__.py
jsonfield/tests/jsonfield_test_app/forms.py
jsonfield/tests/jsonfield_test_app/models.py
django_jsonfieldI-1.4.1.dist-info/LICENSE
django_jsonfieldI-1.4.1.dist-info/METADATA
django_jsonfieldI-1.4.1.dist-info/WHEEL
django_jsonfieldI-1.4.1.dist-info/top_level.txt
django_jsonfieldI-1.4.1.dist-info/RECORD
