Metadata-Version: 2.1
Name: django-jsonfieldI
Version: 1.4.1
Summary: JSONField for django models
Home-page: https://github.com/insedhuma/django-jsonfield
Author: Jack Chipofya
Author-email: hadatintelligence@outlook.com
Maintainer: Jack Chipofya
Maintainer-email: hadatintelligence@outlook.com
Classifier: Development Status :: 6 - Mature
Classifier: Framework :: Django
Classifier: Framework :: Django :: 1.11
Classifier: Framework :: Django :: 2.0
Classifier: Framework :: Django :: 2.1
Classifier: Framework :: Django :: 2.2
Classifier: Intended Audience :: Developers
Classifier: License :: OSI Approved :: BSD License
Classifier: Operating System :: OS Independent
Classifier: Programming Language :: Python
Classifier: Programming Language :: Python :: 2
Classifier: Programming Language :: Python :: 3
License-File: LICENSE
Requires-Dist: Django (>=1.11)
Requires-Dist: six
